mcp_1/__init__.py
mcp_1/config.py
mcp_1/server.py
mcp_1/store.py
mcp_1/data/demo_cases.db
mcp_case_server-0.2.0.dist-info/METADATA
mcp_case_server-0.2.0.dist-info/WHEEL
mcp_case_server-0.2.0.dist-info/entry_points.txt
mcp_case_server-0.2.0.dist-info/licenses/LICENSE
mcp_case_server-0.2.0.dist-info/RECORD
