Metadata-Version: 2.4
Name: mcp-case-server
Version: 0.2.0
Summary: 一個支援雙模式（Demo SQLite / PostgreSQL）的 MCP Server，提供案件查詢功能
Author-email: plion818 <patrick89818pp@gmail.com>
License: MIT
License-File: LICENSE
Requires-Python: >=3.10
Requires-Dist: mcp[cli]>=1.0.0
Requires-Dist: psycopg[binary]>=3.2.0
Requires-Dist: sqlalchemy>=2.0.0
